setup.cfg
setup.py
beantool/__init__.py
beantool.egg-info/PKG-INFO
beantool.egg-info/SOURCES.txt
beantool.egg-info/dependency_links.txt
beantool.egg-info/entry_points.txt
beantool.egg-info/not-zip-safe
beantool.egg-info/requires.txt
beantool.egg-info/top_level.txt
beantool/handlers/__init__.py
beantool/handlers/handler_base.py
beantool/handlers/job.py
beantool/handlers/server.py
beantool/handlers/tube.py
scripts/bt