Metadata-Version: 1.1
Name: beantool
Version: 0.2.4dev
Summary: A beanstalkd console client.
Home-page: https://github.com/dsoprea/BeanTool
Author: Dustin Oprea
Author-email: myselfasunder@gmail.com
License: GPL 2
Keywords: beanstalk beanstalkd queue
Platform: UNKNOWN
Classifier: Development Status :: 3 - Alpha
Classifier: Environment :: Console
Classifier: Intended Audience :: System Administrators
Classifier: License :: OSI Approved :: GNU General Public License v2 (GPLv2)
